CTSgetPy/CTSgetPy.py
CTSgetPy/__init__.py
CTSgetPy-0.0.2.dist-info/METADATA
CTSgetPy-0.0.2.dist-info/RECORD
CTSgetPy-0.0.2.dist-info/WHEEL
CTSgetPy-0.0.2.dist-info/top_level.txt
