Metadata-Version: 2.1
Name: CTSgetPy
Version: 0.0.2
Summary: Python interface to Chemical Translation Service (CTS)
Home-page: https://github.com/hcji/CTSgetPy
Author: Hongchao Ji
Author-email: ji.hongchao@foxmail.com
License: MIT
Platform: UNKNOWN
Classifier: Development Status :: 4 - Beta
Classifier: Programming Language :: Python :: 3.6
Classifier: Programming Language :: Python :: 3.7
Requires-Dist: requests
Requires-Dist: tqdm
Requires-Dist: bs4
